pygameprogress/__init__.py
pygameprogress/animation.py
pygameprogress/bars.py
pygameprogress/sprites.py
pygameprogress/usage.py
pygameprogress-0.2.1.dist-info/METADATA
pygameprogress-0.2.1.dist-info/WHEEL
pygameprogress-0.2.1.dist-info/top_level.txt
pygameprogress-0.2.1.dist-info/RECORD
