Metadata-Version: 2.4
Name: pygameprogress
Version: 0.2.1
Summary: Modular progress bar system for Pygame projects
Home-page: https://github.com/yourusername/pygameprogress
Author: Wilder
Classifier: Programming Language :: Python :: 3
Classifier: License :: OSI Approved :: MIT License
Classifier: Operating System :: OS Independent
Classifier: Topic :: Games/Entertainment
Classifier: Topic :: Software Development :: Libraries :: Python Modules
Requires-Python: >=3.7
Requires-Dist: pygame>=2.0.0
Dynamic: author
Dynamic: classifier
Dynamic: description-content-type
Dynamic: home-page
Dynamic: requires-dist
Dynamic: requires-python
Dynamic: summary
